JCP_HiveConnect/Client.py
JCP_HiveConnect/HiveConnect.py
JCP_HiveConnect/__init__.py
JCP_HiveConnect-0.0.3.dist-info/LICENSE.txt
JCP_HiveConnect-0.0.3.dist-info/METADATA
JCP_HiveConnect-0.0.3.dist-info/WHEEL
JCP_HiveConnect-0.0.3.dist-info/top_level.txt
JCP_HiveConnect-0.0.3.dist-info/RECORD
