Metadata-Version: 2.1
Name: JCP-HiveConnect
Version: 0.0.3
Summary: A JCP Hive package
Home-page: https://github.com/pypa/sampleproject
Author: Ratnesh Kumar
Author-email: rkumar27@jcp.com
License: UNKNOWN
Platform: UNKNOWN
Classifier: Programming Language :: Python :: 3
Classifier: License :: OSI Approved :: MIT License
Classifier: Operating System :: OS Independent
Requires-Dist: paramiko
Requires-Dist: pandas
